e_qsl-0.5.0.dist-info/licenses/LICENSE
eqsl/__init__.py
eqsl/_eqsl.py
eqsl/_version.py
eqsl/sendcard.py
eqsl/card/default.jpg
eqsl/fonts/DroidSansMono.ttf
eqsl/fonts/Ubuntu Mono derivative Powerline Bold.ttf
eqsl/fonts/VeraMono-Italic.ttf
e_qsl-0.5.0.dist-info/METADATA
e_qsl-0.5.0.dist-info/WHEEL
e_qsl-0.5.0.dist-info/entry_points.txt
e_qsl-0.5.0.dist-info/top_level.txt
e_qsl-0.5.0.dist-info/RECORD
