Metadata-Version: 2.4
Name: e-qsl
Version: 0.5.0
Summary: Send contacts confirmation cards (QSL Cards).
Author: Fred C. (W6BSD)
License: BSD 3-Clause License
Project-URL: Documentation, https://github.com/0x9900/QSL/
Project-URL: Source, https://github.com/0x9900/QSL
Project-URL: Tracker, https://github.com/0x9900/QSL/issues
Classifier: Intended Audience :: End Users/Desktop
Classifier: Intended Audience :: Telecommunications Industry
Classifier: License :: OSI Approved :: BSD License
Classifier: Operating System :: OS Independent
Classifier: Programming Language :: Python :: 3.10
Classifier: Programming Language :: Python :: 3.11
Classifier: Programming Language :: Python :: 3.12
Classifier: Programming Language :: Python
Classifier: Topic :: Communications :: Ham Radio
Requires-Python: >=3.10
License-File: LICENSE
Requires-Dist: Pillow
Requires-Dist: PyYAML
Requires-Dist: adif_io
Requires-Dist: watchfiles
Requires-Dist: qrzlib>=2.0.0
Requires-Dist: jinja2>=3.1.6
Provides-Extra: dev
Requires-Dist: pre-commit; extra == "dev"
Requires-Dist: ipdb; extra == "dev"
Requires-Dist: flake8; extra == "dev"
Requires-Dist: mypy; extra == "dev"
Requires-Dist: isort; extra == "dev"
Requires-Dist: pytest; extra == "dev"
Requires-Dist: pytest-cov; extra == "dev"
Dynamic: license-file
